pyohio/__init__.py
pyohio/_version.py
pyohio/cli.py
pyohio/schedule.py
pyohio-0.0.3.dist-info/DESCRIPTION.rst
pyohio-0.0.3.dist-info/METADATA
pyohio-0.0.3.dist-info/RECORD
pyohio-0.0.3.dist-info/WHEEL
pyohio-0.0.3.dist-info/entry_points.txt
pyohio-0.0.3.dist-info/metadata.json
pyohio-0.0.3.dist-info/top_level.txt
