Metadata-Version: 2.0
Name: pyohio
Version: 0.0.3
Summary: PyOhio-related tools.
Home-page: https://github.com/tylerdave/pyohio
Author: Dave Forgac
Author-email: tylerdave@tylerdave.com
License: MIT
Keywords: pyohio
Platform: UNKNOWN
Classifier: Development Status :: 2 - Pre-Alpha
Classifier: Intended Audience :: Developers
Classifier: License :: OSI Approved :: MIT License
Classifier: Natural Language :: English
Classifier: Programming Language :: Python :: 2
Classifier: Programming Language :: Python :: 2.7
Classifier: Programming Language :: Python :: 3
Classifier: Programming Language :: Python :: 3.3
Classifier: Programming Language :: Python :: 3.4
Classifier: Programming Language :: Python :: 3.5
Requires-Dist: click
Requires-Dist: colorama
Requires-Dist: python-dateutil
Requires-Dist: requests
Requires-Dist: requests-cache
Requires-Dist: tabulate
